.flake8
.gitignore
.travis.yml
LICENSE
README.md
setup.cfg
setup.py
mapbind/__init__.py
mapbind.egg-info/PKG-INFO
mapbind.egg-info/SOURCES.txt
mapbind.egg-info/dependency_links.txt
mapbind.egg-info/top_level.txt
tests/__init__.py