Metadata-Version: 1.2
Name: mapbind
Version: 1.0
Summary: Assignment-aware binding functions
Home-page: https://github.com/obriencj/python-mapbind
Author: Christopher O'Brien
Author-email: obriencj@gmail.com
License: GNU Lesser General Public License v.3
Download-URL: https://github.com/obriencj/python-mapbind/archive/v1.0.0.tar.gz
Platform: UNKNOWN
Classifier: Intended Audience :: Developers
Classifier: Programming Language :: Python :: 2.6
Classifier: Programming Language :: Python :: 2.7
Classifier: Programming Language :: Python :: 3.3
Classifier: Programming Language :: Python :: 3.4
Classifier: Programming Language :: Python :: 3.5
Classifier: Programming Language :: Python :: 3.6
Classifier: Programming Language :: Python :: Implementation :: CPython
Classifier: Programming Language :: Python :: Implementation :: PyPy
Classifier: Topic :: Software Development
Requires-Python: >=2.6, !=3.0.*, !=3.1.*, !=3.2.*, <4
